{"@timestamp":"2026-01-19T00:28:41.080Z","log.level": "INFO","message":"Commencing graceful shutdown. Waiting for active requests to complete","ecs.version": "1.2.0","service.name":"serviceB","event.dataset":"serviceB","process.thread.name":"SpringApplicationShutdownHook","log.logger":"org.springframework.boot.web.embedded.tomcat.GracefulShutdown"}
{"@timestamp":"2026-01-19T00:28:41.162Z","log.level": "INFO","message":"Graceful shutdown complete","ecs.version": "1.2.0","service.name":"serviceB","event.dataset":"serviceB","process.thread.name":"tomcat-shutdown","log.logger":"org.springframework.boot.web.embedded.tomcat.GracefulShutdown"}
